[
  {
    "name":"告白气球",
    "singer": "周杰伦",
    "album": "周杰伦的床边故事",
    "time": "03:35",
    "link_url":"/static/source/告白气球.mp3",
    "cover":"/static/source/告白气球.jpg",
    "link_lrc":"/static/source/告白气球.txt"
  },
  {
    "name":"As long AS Love Me",
    "singer": "Justin Bieber",
    "album": "NOW That's What I Call Music! 44",
    "time": "03:49",
    "link_url":"/static/source/AslongASLoveMe.mp3",
    "cover": "/static/source/AslongASLoveMe.jpg",
    "link_lrc": "/static/source/AslongASLoveMe.txt"
  },
  {
    "name":"Something Just Like This",
    "singer": "Chainsmokers",
    "album": "Something Just Like This",
    "time": "04:07",
    "link_url":"/static/source/SomethingJustLikeThis.mp3",
    "cover":"/static/source/SomethingJustLikeThis.jpg",
    "link_lrc":"/static/source/SomethingJustLikeThis.txt"
  },

  {
    "name":"凉凉",
    "singer": "杨宗纬/张碧晨",
    "album": "凉凉",
    "time": "05:00",
    "link_url":"/static/source/凉凉.mp3",
    "cover":"/static/source/凉凉.jpg",
    "link_lrc":"/static/source/凉凉.txt"
  },
  {
    "name":"小城大事",
    "singer": "张学友",
    "album": "学友光年世界巡迴演唱会",
    "time": "03:54",
    "link_url":"/static/source/小城大事.mp3",
    "cover":"/static/source/小城大事.jpg",
    "link_lrc":"/static/source/小城大事.txt"
  },
  {
    "name":"广东爱情故事",
    "singer": "广东雨神",
    "album": "广东爱情故事",
    "time": "03:34",
    "link_url":"/static/source/广东爱情故事.mp3",
    "cover":"/static/source/广东爱情故事.jpg",
    "link_lrc":"/static/source/广东爱情故事.txt"
  },
  {
    "name":"演员",
    "singer": "薛之谦",
    "album": "绅士",
    "time": "04:21",
    "link_url":"/static/source/演员.mp3",
    "cover":"/static/source/演员.jpg",
    "link_lrc":"/static/source/演员.txt"},


  {
    "name":"输了你赢了世界又如何",
    "singer": "林俊杰",
    "album": "梦想的声音《第二季》",
    "time": "04:43",
    "link_url":"/static/source/输了你赢了世界又如何.mp3",
    "cover":"/static/source/输了你赢了世界又如何.jpg",
    "link_lrc":"/static/source/输了你赢了世界又如何.txt"
  }
]